{"uuid":"b6e39a4b-339a-4eaf-acf3-7b92a20dd2fe","token_id":1164,"color":4,"transactions":[{"timestamp":1634213307,"price":0.10301,"block_number":13416224,"account":{"address":"0x3426862cf088e733d62437ce9e29c73bca04eb9e","tx_count":75,"eth":{"value":"1.76811195070486067","dynamic":"1.23358051370486067"},"nft":{"value":36,"dynamic":33,"collections":[false,false,false,false,false,false,false],"collections2":{"89seconds":false,"artBlocks":false,"boredApes":false,"cryptoPunks":false,"ksoids":false,"meebits":false,"omnimorphs":false}}},"floor":0.10301},{"timestamp":1634832974,"price":0.123,"block_number":13462030,"account":{"address":"0xbf5b9dc2f456b60c06a7658f064e390e4d7b4fe5","tx_count":88,"eth":{"value":"0.133208110000924371","dynamic":"0.133208110000924371"},"nft":{"value":39,"dynamic":39,"collections":[false,false,false,false,false,false,false],"collections2":{"89seconds":false,"artBlocks":false,"boredApes":false,"cryptoPunks":false,"ksoids":false,"meebits":false,"omnimorphs":false}}},"floor":0.1036719},{"timestamp":1635362532,"price":0.1479,"block_number":13501215,"account":{"address":"0x2638ff4bdbbba6930a014b84e848ad3f70253bd8","tx_count":617,"eth":{"value":"0.780227365265361835","dynamic":"-1.516225837597574154"},"nft":{"value":165,"dynamic":132,"collections":[false,false,false,false,false,false,false],"collections2":{"89seconds":false,"artBlocks":false,"boredApes":false,"cryptoPunks":false,"ksoids":false,"meebits":false,"omnimorphs":false}}},"floor":0.10301}]}