{"uuid":"452fc790-146b-41fa-a56c-028cf66e6511","token_id":1324,"color":4,"transactions":[{"timestamp":1634214564,"price":0.10301,"block_number":13416323,"account":{"address":"0x08c65dd23982d6e30a678c54a4aa9245c0d1b80f","tx_count":199,"eth":{"value":"1.389433254939224501","dynamic":"1.369678147081139472"},"nft":{"value":19,"dynamic":19,"collections":[false,false,false,false,false,false,false],"collections2":{"89seconds":false,"artBlocks":false,"boredApes":false,"cryptoPunks":false,"ksoids":false,"meebits":false,"omnimorphs":false}}},"floor":0.10301},{"timestamp":1634219666,"price":0.22,"block_number":13416684,"account":{"address":"0xc35a5fec6be6957899e15559be252db882220b37","tx_count":28949,"eth":{"value":"53.525763812986571374","dynamic":"39.283434362305199933"},"nft":{"value":6514,"dynamic":482,"collections":[false,false,false,false,false,false,false],"collections2":{"89seconds":false,"artBlocks":true,"boredApes":false,"cryptoPunks":false,"ksoids":true,"meebits":false,"omnimorphs":false}}},"floor":0.10301},{"timestamp":1634231680,"price":0.43,"block_number":13417611,"account":{"address":"0x6e5e3a5dfb5d218bd81d8083f11aeac7656ea668","tx_count":127,"eth":{"value":"0.147135492135629014","dynamic":"-0.027376209541746895"},"nft":{"value":39,"dynamic":39,"collections":[false,false,false,false,false,false,false],"collections2":{"89seconds":false,"artBlocks":false,"boredApes":false,"cryptoPunks":false,"ksoids":false,"meebits":false,"omnimorphs":true}}},"floor":0.10301},{"timestamp":1634242142,"price":0.5,"block_number":13418364,"account":{"address":"0x13e48abf4248251934a7d14c857c89e996243851","tx_count":197,"eth":{"value":"0.411772485303431928","dynamic":"0.411772485303431928"},"nft":{"value":153,"dynamic":153,"collections":[false,false,false,false,false,false,false],"collections2":{"89seconds":false,"artBlocks":false,"boredApes":false,"cryptoPunks":false,"ksoids":false,"meebits":false,"omnimorphs":true}}},"floor":0.10301},{"timestamp":1635870616,"price":0.288,"block_number":13538596,"account":{"address":"0x7c219173f54e3ad9cf02f440639316feff40946f","tx_count":30,"eth":{"value":"3.833958462219407","dynamic":"3.833958462219407"},"nft":{"value":24,"dynamic":24,"collections":[false,false,false,false,false,false,false],"collections2":{"89seconds":false,"artBlocks":false,"boredApes":false,"cryptoPunks":false,"ksoids":false,"meebits":true,"omnimorphs":false}}},"floor":0.058929645383502566},{"timestamp":1640979336,"price":0.065,"block_number":13915000,"account":{"address":"0x7c219173f54e3ad9cf02f440639316feff40946f","tx_count":50,"eth":{"value":"0.443912610423205994","dynamic":"-1.200457851576794006"},"nft":{"value":24,"dynamic":17,"collections":[false,false,false,false,false,false,false],"collections2":{"89seconds":false,"artBlocks":false,"boredApes":false,"cryptoPunks":false,"ksoids":false,"meebits":true,"omnimorphs":false}}},"floor":0.0599},{"timestamp":1640980423,"price":0.065,"block_number":13915084,"account":{"address":"0x84d763dae3ad34d63050d7288485f3f49877ed27","tx_count":68,"eth":{"value":"0.27149342397807663","dynamic":"-0.099008490515126305"},"nft":{"value":18,"dynamic":15,"collections":[false,false,false,false,false,false,false],"collections2":{"89seconds":false,"artBlocks":false,"boredApes":false,"cryptoPunks":false,"ksoids":false,"meebits":true,"omnimorphs":false}}},"floor":0.0599}]}