{"uuid":"ee537dfe-e7a1-485f-97b4-cfc3355d97a9","token_id":1351,"color":0,"transactions":[{"timestamp":1634214874,"price":0.10301,"block_number":13416352,"account":{"address":"0x755562cf09a070cf2afeb8271ed840ae78a373a8","tx_count":42,"eth":{"value":"0.047646017472455039","dynamic":"0.047646017472455039"},"nft":{"value":0,"dynamic":0,"collections":[false,false,false,false,false,false,false],"collections2":{"89seconds":false,"artBlocks":false,"boredApes":false,"cryptoPunks":false,"ksoids":false,"meebits":false,"omnimorphs":false}}},"floor":0.10301},{"timestamp":1636026857,"price":0.1,"block_number":13550050,"account":{"address":"0x8dbbca57ea56290efa14d835bbfd34faf1d89753","tx_count":3392,"eth":{"value":"4.039063962134966052","dynamic":"-13.251943036138187502"},"nft":{"value":2496,"dynamic":805,"collections":[false,false,false,false,false,false,false],"collections2":{"89seconds":true,"artBlocks":true,"boredApes":true,"cryptoPunks":true,"ksoids":true,"meebits":true,"omnimorphs":false}}},"floor":0.05301},{"timestamp":1636241561,"price":0.12,"block_number":13565913,"account":{"address":"0xc35a5fec6be6957899e15559be252db882220b37","tx_count":29667,"eth":{"value":"14.475704268992623325","dynamic":"13.49184087788441623"},"nft":{"value":6816,"dynamic":-2339,"collections":[false,false,false,false,false,false,false],"collections2":{"89seconds":true,"artBlocks":true,"boredApes":true,"cryptoPunks":true,"ksoids":true,"meebits":true,"omnimorphs":false}}},"floor":0.07301},{"timestamp":1636245304,"price":0.12,"block_number":13566223,"account":{"address":"0x8dbbca57ea56290efa14d835bbfd34faf1d89753","tx_count":3428,"eth":{"value":"3.253518761489503439","dynamic":"-11.161637736082060583"},"nft":{"value":2500,"dynamic":816,"collections":[false,false,false,false,false,false,false],"collections2":{"89seconds":true,"artBlocks":true,"boredApes":true,"cryptoPunks":true,"ksoids":true,"meebits":true,"omnimorphs":false}}},"floor":0.07301},{"timestamp":1637330942,"price":0.09,"block_number":13645989,"account":{"address":"0x8dbbca57ea56290efa14d835bbfd34faf1d89753","tx_count":3468,"eth":{"value":"5.689951433898959094","dynamic":"0.578053090680985429"},"nft":{"value":1536,"dynamic":794,"collections":[false,false,false,false,false,false,false],"collections2":{"89seconds":true,"artBlocks":true,"boredApes":true,"cryptoPunks":true,"ksoids":true,"meebits":true,"omnimorphs":false}}},"floor":0.095}]}