{"uuid":"ef81faa4-3547-41f8-811e-a83d2c21ff6f","token_id":1638,"color":3,"transactions":[{"timestamp":1634218077,"price":0.10301,"block_number":13416570,"account":{"address":"0x71248fe5224be1c7dfb934b26f1d13ddbbab48cb","tx_count":149,"eth":{"value":"0.040118546920002492","dynamic":"0.03491014206963089"},"nft":{"value":50,"dynamic":48,"collections":[false,false,false,false,false,false,false],"collections2":{"89seconds":false,"artBlocks":false,"boredApes":false,"cryptoPunks":false,"ksoids":false,"meebits":false,"omnimorphs":false}}},"floor":0.10301}]}