{"uuid":"3e96e3f5-5f96-4b02-82bc-dcc8646c75b2","token_id":2561,"color":4,"transactions":[{"timestamp":1634241251,"price":0.10301,"block_number":13418283,"account":{"address":"0xaf3932781d8bc7ad6ddf45d2a0bdf4132686bad2","tx_count":119,"eth":{"value":"0.24377607590688958","dynamic":"0.24377607590688958"},"nft":{"value":0,"dynamic":0,"collections":[false,false,false,false,false,false,false],"collections2":{"89seconds":false,"artBlocks":false,"boredApes":false,"cryptoPunks":false,"ksoids":false,"meebits":false,"omnimorphs":false}}},"floor":0.10301},{"timestamp":1634251687,"price":0.2,"block_number":13419070,"account":{"address":"0xcd5e5f1457486eb5a00238c7d4ab9a08aa15160b","tx_count":36,"eth":{"value":"0.182488468127646814","dynamic":"0.162059836377646814"},"nft":{"value":14,"dynamic":14,"collections":[false,false,false,false,false,false,false],"collections2":{"89seconds":false,"artBlocks":false,"boredApes":false,"cryptoPunks":false,"ksoids":false,"meebits":false,"omnimorphs":false}}},"floor":0.10301},{"timestamp":1634959881,"price":0.14,"block_number":13471474,"account":{"address":"0xbe5be517537e53f09e88bcdf61da238477dca226","tx_count":161,"eth":{"value":"1.968650730088164469","dynamic":"1.968650730088164469"},"nft":{"value":54,"dynamic":54,"collections":[false,false,false,false,false,false,false],"collections2":{"89seconds":false,"artBlocks":false,"boredApes":false,"cryptoPunks":false,"ksoids":false,"meebits":false,"omnimorphs":false}}},"floor":0.135},{"timestamp":1634960903,"price":0.14,"block_number":13471539,"account":{"address":"0x4184740fd5ff75b1d66aaddd5b9b5772296f8f46","tx_count":415,"eth":{"value":"0.103603095500943826","dynamic":"0.094500428984203505"},"nft":{"value":178,"dynamic":136,"collections":[false,false,false,false,false,false,false],"collections2":{"89seconds":false,"artBlocks":false,"boredApes":false,"cryptoPunks":false,"ksoids":false,"meebits":false,"omnimorphs":false}}},"floor":0.135},{"timestamp":1634961838,"price":0.14,"block_number":13471610,"account":{"address":"0xbe5be517537e53f09e88bcdf61da238477dca226","tx_count":163,"eth":{"value":"2.328331180088164469","dynamic":"2.328331180088164469"},"nft":{"value":53,"dynamic":53,"collections":[false,false,false,false,false,false,false],"collections2":{"89seconds":false,"artBlocks":false,"boredApes":false,"cryptoPunks":false,"ksoids":false,"meebits":false,"omnimorphs":false}}},"floor":0.135},{"timestamp":1634963028,"price":0.14,"block_number":13471687,"account":{"address":"0x4184740fd5ff75b1d66aaddd5b9b5772296f8f46","tx_count":417,"eth":{"value":"0.066905695500943826","dynamic":"0.057803028984203505"},"nft":{"value":178,"dynamic":136,"collections":[false,false,false,false,false,false,false],"collections2":{"89seconds":false,"artBlocks":false,"boredApes":false,"cryptoPunks":false,"ksoids":false,"meebits":false,"omnimorphs":false}}},"floor":0.135},{"timestamp":1634969167,"price":0.14,"block_number":13472108,"account":{"address":"0xcd5e5f1457486eb5a00238c7d4ab9a08aa15160b","tx_count":64,"eth":{"value":"0.182412940666949744","dynamic":"0.161984308916949744"},"nft":{"value":26,"dynamic":26,"collections":[false,false,false,false,false,false,false],"collections2":{"89seconds":false,"artBlocks":false,"boredApes":false,"cryptoPunks":false,"ksoids":false,"meebits":false,"omnimorphs":false}}},"floor":0.12150000000000001}]}