{"uuid":"68dfc45a-ae3b-4243-83f2-faf959969b75","token_id":2753,"color":1,"transactions":[{"timestamp":1634260441,"price":0.10301,"block_number":13419676,"account":{"address":"0xc5b0d67b004563d633ba58a198441e992a12b04d","tx_count":27,"eth":{"value":"9.385374251787435291","dynamic":"0.449134424787435291"},"nft":{"value":11,"dynamic":-3,"collections":[false,false,false,false,false,false,false],"collections2":{"89seconds":false,"artBlocks":false,"boredApes":false,"cryptoPunks":false,"ksoids":true,"meebits":false,"omnimorphs":false}}},"floor":0.10301},{"timestamp":1637403265,"price":0.09666666666666666,"block_number":13651301,"account":{"address":"0xd4ffd5bdc785fe5f8b8d3568ab43b8da8492ca4d","tx_count":207,"eth":{"value":"5973.0927171577251635","dynamic":"1780.4191421193915686"},"nft":{"value":189,"dynamic":188,"collections":[false,false,false,false,false,false,false],"collections2":{"89seconds":false,"artBlocks":false,"boredApes":false,"cryptoPunks":false,"ksoids":false,"meebits":false,"omnimorphs":false}}},"floor":0.098},{"timestamp":1637489170,"price":0.1,"block_number":13657528,"account":{"address":"0xc5b0d67b004563d633ba58a198441e992a12b04d","tx_count":135,"eth":{"value":"33.90363800647654044","dynamic":"24.96739817947654044"},"nft":{"value":106,"dynamic":106,"collections":[false,false,false,false,false,false,false],"collections2":{"89seconds":false,"artBlocks":false,"boredApes":false,"cryptoPunks":false,"ksoids":false,"meebits":false,"omnimorphs":false}}},"floor":0.09},{"timestamp":1640357293,"price":0.06,"block_number":13868518,"account":{"address":"0xd4ffd5bdc785fe5f8b8d3568ab43b8da8492ca4d","tx_count":251,"eth":{"value":"5818.637539457202752","dynamic":"1625.9639644188691572"},"nft":{"value":67,"dynamic":66,"collections":[false,false,false,false,false,false,false],"collections2":{"89seconds":false,"artBlocks":false,"boredApes":false,"cryptoPunks":true,"ksoids":false,"meebits":false,"omnimorphs":false}}},"floor":0.0499},{"timestamp":1640382482,"price":0.05862068965517241,"block_number":13870419,"account":{"address":"0xc5b0d67b004563d633ba58a198441e992a12b04d","tx_count":189,"eth":{"value":"74.97855633652108845","dynamic":"66.042316509521088445"},"nft":{"value":60,"dynamic":60,"collections":[false,false,false,false,false,false,false],"collections2":{"89seconds":false,"artBlocks":false,"boredApes":false,"cryptoPunks":true,"ksoids":false,"meebits":false,"omnimorphs":false}}},"floor":0.05},{"timestamp":1640399932,"price":0.060714285714285714,"block_number":13871686,"account":{"address":"0xd4ffd5bdc785fe5f8b8d3568ab43b8da8492ca4d","tx_count":261,"eth":{"value":"5818.607234092755585","dynamic":"1625.93365905442199"},"nft":{"value":31,"dynamic":30,"collections":[false,false,false,false,false,false,false],"collections2":{"89seconds":false,"artBlocks":false,"boredApes":false,"cryptoPunks":true,"ksoids":false,"meebits":false,"omnimorphs":false}}},"floor":0.05},{"timestamp":1640447389,"price":0.05862068965517241,"block_number":13875258,"account":{"address":"0xc5b0d67b004563d633ba58a198441e992a12b04d","tx_count":200,"eth":{"value":"75.07113834409053864","dynamic":"66.134898517090538635"},"nft":{"value":29,"dynamic":29,"collections":[false,false,false,false,false,false,false],"collections2":{"89seconds":false,"artBlocks":false,"boredApes":false,"cryptoPunks":true,"ksoids":false,"meebits":false,"omnimorphs":false}}},"floor":0.05}]}