{"uuid":"ddca19ce-73c5-4167-8a8e-90bd0dc9a699","token_id":2813,"color":3,"transactions":[{"timestamp":1634267346,"price":0.10301,"block_number":13420176,"account":{"address":"0xbca5a56465c9a3f3a19c0617ac9ab5f56877d69e","tx_count":74,"eth":{"value":"4.65415096941123421","dynamic":"4.65415096941123421"},"nft":{"value":25,"dynamic":25,"collections":[false,false,false,false,false,false,false],"collections2":{"89seconds":false,"artBlocks":false,"boredApes":false,"cryptoPunks":false,"ksoids":false,"meebits":false,"omnimorphs":false}}},"floor":0.10301},{"timestamp":1634279849,"price":0.001,"block_number":13421066,"account":{"address":"0xcab38f1c738042e1e1208da1d4c6e53dd83c80df","tx_count":512,"eth":{"value":"1.866982332558544435","dynamic":"1.866982332558544435"},"nft":{"value":143,"dynamic":143,"collections":[false,false,false,false,false,false,false],"collections2":{"89seconds":false,"artBlocks":false,"boredApes":false,"cryptoPunks":false,"ksoids":false,"meebits":false,"omnimorphs":false}}},"floor":0.2},{"timestamp":1634280299,"price":0.001,"block_number":13421099,"account":{"address":"0xbca5a56465c9a3f3a19c0617ac9ab5f56877d69e","tx_count":76,"eth":{"value":"4.627294779488432299","dynamic":"4.627294779488432299"},"nft":{"value":25,"dynamic":25,"collections":[false,false,false,false,false,false,false],"collections2":{"89seconds":false,"artBlocks":false,"boredApes":false,"cryptoPunks":false,"ksoids":false,"meebits":false,"omnimorphs":false}}},"floor":0.2},{"timestamp":1634300492,"price":0.39,"block_number":13422604,"account":{"address":"0xca18e80f5d68ba305a1411a16a9fdf68e8ed915e","tx_count":6,"eth":{"value":"1.58720231304179085","dynamic":"1.58720231304179085"},"nft":{"value":0,"dynamic":0,"collections":[false,false,false,false,false,false,false],"collections2":{"89seconds":false,"artBlocks":false,"boredApes":false,"cryptoPunks":false,"ksoids":false,"meebits":false,"omnimorphs":false}}},"floor":0.1791},{"timestamp":1634835267,"price":0.0746,"block_number":13462209,"account":{"address":"0x0694969e24a5c2bbdea00b55906c25daffc667f2","tx_count":10,"eth":{"value":"0.342028069238374243","dynamic":"0.342028069238374243"},"nft":{"value":0,"dynamic":0,"collections":[false,false,false,false,false,false,false],"collections2":{"89seconds":false,"artBlocks":false,"boredApes":false,"cryptoPunks":false,"ksoids":false,"meebits":false,"omnimorphs":false}}},"floor":0.10301},{"timestamp":1634838212,"price":0.12078,"block_number":13462439,"account":{"address":"0x8f445aa67c45805dd9a99f3a7224cbd3ba5ef569","tx_count":238,"eth":{"value":"0.912508719288436038","dynamic":"-0.936776587519591391"},"nft":{"value":86,"dynamic":70,"collections":[false,false,false,false,false,false,false],"collections2":{"89seconds":false,"artBlocks":false,"boredApes":false,"cryptoPunks":false,"ksoids":false,"meebits":false,"omnimorphs":false}}},"floor":0.12799},{"timestamp":1634841054,"price":0.15,"block_number":13462641,"account":{"address":"0x55f162642c8702a130a39c5ffb2fd7a24d00dd02","tx_count":328,"eth":{"value":"0.164109592714160301","dynamic":"0.164109592714160301"},"nft":{"value":119,"dynamic":119,"collections":[false,false,false,false,false,false,false],"collections2":{"89seconds":false,"artBlocks":false,"boredApes":false,"cryptoPunks":false,"ksoids":false,"meebits":false,"omnimorphs":true}}},"floor":0.10301}]}