{"uuid":"7c2275ab-2c0c-431c-b79e-086cc69da782","token_id":3406,"color":5,"transactions":[{"timestamp":1634294202,"price":0.10301,"block_number":13422148,"account":{"address":"0xbd1cc8ee52d8f872e94712e80b9d079c8899c44a","tx_count":84,"eth":{"value":"0.058799839043265086","dynamic":"0.058799839043265086"},"nft":{"value":34,"dynamic":34,"collections":[false,false,false,false,false,false,false],"collections2":{"89seconds":false,"artBlocks":false,"boredApes":false,"cryptoPunks":false,"ksoids":false,"meebits":false,"omnimorphs":false}}},"floor":0.10301},{"timestamp":1634307310,"price":0.19,"block_number":13423131,"account":{"address":"0x7f1ec7dff7b4965bf912ee3cafe461c86fc008bc","tx_count":143,"eth":{"value":"0.05010987509272138","dynamic":"0.036024293752584761"},"nft":{"value":53,"dynamic":53,"collections":[false,false,false,false,false,false,false],"collections2":{"89seconds":false,"artBlocks":false,"boredApes":false,"cryptoPunks":false,"ksoids":false,"meebits":false,"omnimorphs":false}}},"floor":0.199},{"timestamp":1634308910,"price":0.25,"block_number":13423252,"account":{"address":"0xf71c76f3449bc86997b69f0cb3702dcb4e01a9c3","tx_count":13,"eth":{"value":"0.006447266995834062","dynamic":"0.006447266995834062"},"nft":{"value":8,"dynamic":8,"collections":[false,false,false,false,false,false,false],"collections2":{"89seconds":false,"artBlocks":false,"boredApes":false,"cryptoPunks":false,"ksoids":false,"meebits":false,"omnimorphs":false}}},"floor":0.199},{"timestamp":1634901406,"price":0.13,"block_number":13467101,"account":{"address":"0xafa3a87e6b4179552615faaf3c600d00016d10a1","tx_count":28,"eth":{"value":"0.225284351776928108","dynamic":"-26.774715648223071892"},"nft":{"value":25,"dynamic":25,"collections":[false,false,false,false,false,false,false],"collections2":{"89seconds":false,"artBlocks":false,"boredApes":false,"cryptoPunks":true,"ksoids":false,"meebits":false,"omnimorphs":false}}},"floor":0.10301},{"timestamp":1634992373,"price":0.16,"block_number":13473766,"account":{"address":"0xf71c76f3449bc86997b69f0cb3702dcb4e01a9c3","tx_count":17,"eth":{"value":"0.047458432203179952","dynamic":"0.047458432203179952"},"nft":{"value":9,"dynamic":9,"collections":[false,false,false,false,false,false,false],"collections2":{"89seconds":false,"artBlocks":false,"boredApes":false,"cryptoPunks":false,"ksoids":false,"meebits":false,"omnimorphs":false}}},"floor":0.12150000000000001},{"timestamp":1635002521,"price":0.14,"block_number":13474547,"account":{"address":"0x5c4fe960950ba0e09a72869c3d51fe70f07580e0","tx_count":212,"eth":{"value":"0.910590419839301056","dynamic":"-91.380879570990892216"},"nft":{"value":237,"dynamic":199,"collections":[false,false,false,false,false,false,false],"collections2":{"89seconds":false,"artBlocks":true,"boredApes":true,"cryptoPunks":true,"ksoids":false,"meebits":false,"omnimorphs":false}}},"floor":0.14},{"timestamp":1635003330,"price":0.16,"block_number":13474603,"account":{"address":"0xf71c76f3449bc86997b69f0cb3702dcb4e01a9c3","tx_count":19,"eth":{"value":"0.963167891913365032","dynamic":"0.963167891913365032"},"nft":{"value":9,"dynamic":9,"collections":[false,false,false,false,false,false,false],"collections2":{"89seconds":false,"artBlocks":false,"boredApes":false,"cryptoPunks":false,"ksoids":false,"meebits":false,"omnimorphs":false}}},"floor":0.14}]}