{"uuid":"7c83df1b-cb07-476e-86a0-9f96f77899c9","token_id":4011,"color":4,"transactions":[{"timestamp":1634354282,"price":0.10301,"block_number":13426591,"account":{"address":"0x6722cadb57fc2edc4033d293b77f0687578b5384","tx_count":1,"eth":{"value":"0.12714818930178936","dynamic":"0.12714818930178936"},"nft":{"value":2,"dynamic":2,"collections":[false,false,false,false,false,false,false],"collections2":{"89seconds":false,"artBlocks":false,"boredApes":false,"cryptoPunks":false,"ksoids":false,"meebits":false,"omnimorphs":false}}},"floor":0.10301}]}