{"uuid":"a90ae18c-36a9-42ad-adbf-ea38baef284e","token_id":4198,"color":0,"transactions":[{"timestamp":1634366258,"price":0.10301,"block_number":13427443,"account":{"address":"0x8bec2899ec28ab294bc19faf500008e5e7037cde","tx_count":76,"eth":{"value":"2.774547248902079386","dynamic":"2.774547248902079386"},"nft":{"value":24,"dynamic":24,"collections":[false,false,false,false,false,false,false],"collections2":{"89seconds":false,"artBlocks":false,"boredApes":false,"cryptoPunks":false,"ksoids":false,"meebits":false,"omnimorphs":false}}},"floor":0.10301},{"timestamp":1634383944,"price":0.158,"block_number":13428773,"account":{"address":"0x9be773d7c6485cd2d964af355d1c2fdbfb6bfa36","tx_count":383,"eth":{"value":"0.055700326450978738","dynamic":"0.011019025175791109"},"nft":{"value":23,"dynamic":17,"collections":[false,false,false,false,false,false,false],"collections2":{"89seconds":false,"artBlocks":false,"boredApes":false,"cryptoPunks":false,"ksoids":false,"meebits":false,"omnimorphs":false}}},"floor":0.11323800000000002},{"timestamp":1635133954,"price":0.158,"block_number":13484282,"account":{"address":"0x38dab69dbfa3f50182779b26083e43be46d6ece0","tx_count":736,"eth":{"value":"0.73861613046217939","dynamic":"0.454816638236589047"},"nft":{"value":161,"dynamic":126,"collections":[false,false,false,false,false,false,false],"collections2":{"89seconds":false,"artBlocks":false,"boredApes":true,"cryptoPunks":false,"ksoids":false,"meebits":false,"omnimorphs":false}}},"floor":0.10301},{"timestamp":1636149425,"price":0.01,"block_number":13559151,"account":{"address":"0x9e9c9d3240e26b4559d0245b60d57af988a31c32","tx_count":93,"eth":{"value":"0.051044967979178104","dynamic":"0.051044967979178104"},"nft":{"value":32,"dynamic":32,"collections":[false,false,false,false,false,false,false],"collections2":{"89seconds":false,"artBlocks":false,"boredApes":false,"cryptoPunks":false,"ksoids":false,"meebits":false,"omnimorphs":false}}},"floor":0.05301},{"timestamp":1637110759,"price":0.005,"block_number":13629896,"account":{"address":"0x7d8d636528797e111781a4b7c1035af542d0aaa4","tx_count":25,"eth":{"value":"0.04027746680472776","dynamic":"0.04027746680472776"},"nft":{"value":9,"dynamic":9,"collections":[false,false,false,false,false,false,false],"collections2":{"89seconds":false,"artBlocks":false,"boredApes":false,"cryptoPunks":false,"ksoids":false,"meebits":false,"omnimorphs":false}}},"floor":0.05301}]}