{"uuid":"e4d14b90-30ff-4622-a964-ebfb0e78f716","token_id":4608,"color":5,"transactions":[{"timestamp":1634396440,"price":0.10301,"block_number":13429705,"account":{"address":"0x6dfa6d2ba2f8d6e16e16e2e0d3cf4666cae62ea9","tx_count":92,"eth":{"value":"0.457524643490744019","dynamic":"-1.433849388036201362"},"nft":{"value":16,"dynamic":16,"collections":[false,false,false,false,false,false,false],"collections2":{"89seconds":false,"artBlocks":false,"boredApes":false,"cryptoPunks":false,"ksoids":false,"meebits":false,"omnimorphs":false}}},"floor":0.10301},{"timestamp":1638009896,"price":0.07,"block_number":13695647,"account":{"address":"0xe9452a904e833d3e64b159581884d196e5ece123","tx_count":25,"eth":{"value":"0.067013492961638769","dynamic":"0.067013492961638769"},"nft":{"value":25,"dynamic":25,"collections":[false,false,false,false,false,false,false],"collections2":{"89seconds":false,"artBlocks":false,"boredApes":false,"cryptoPunks":false,"ksoids":false,"meebits":false,"omnimorphs":false}}},"floor":0.07},{"timestamp":1638014169,"price":0.07,"block_number":13695936,"account":{"address":"0x2e7a5982c2d017bf4adba51c2fa873db079fb151","tx_count":42,"eth":{"value":"0.109175446020406016","dynamic":"0.018252914525751949"},"nft":{"value":8,"dynamic":7,"collections":[false,false,false,false,false,false,false],"collections2":{"89seconds":false,"artBlocks":false,"boredApes":false,"cryptoPunks":false,"ksoids":false,"meebits":false,"omnimorphs":false}}},"floor":0.07},{"timestamp":1638099965,"price":0.07,"block_number":13702200,"account":{"address":"0x6dfa6d2ba2f8d6e16e16e2e0d3cf4666cae62ea9","tx_count":137,"eth":{"value":"0.069312666617302663","dynamic":"-0.008405796946114224"},"nft":{"value":22,"dynamic":21,"collections":[false,false,false,false,false,false,false],"collections2":{"89seconds":false,"artBlocks":false,"boredApes":false,"cryptoPunks":false,"ksoids":false,"meebits":false,"omnimorphs":false}}},"floor":0.08},{"timestamp":1638870536,"price":0.09,"block_number":13757855,"account":{"address":"0xe9452a904e833d3e64b159581884d196e5ece123","tx_count":28,"eth":{"value":"0.029187165118460788","dynamic":"-0.614113208474016138"},"nft":{"value":27,"dynamic":23,"collections":[false,false,false,false,false,false,false],"collections2":{"89seconds":false,"artBlocks":false,"boredApes":false,"cryptoPunks":false,"ksoids":false,"meebits":false,"omnimorphs":false}}},"floor":0.09},{"timestamp":1638966183,"price":0.084,"block_number":13764774,"account":{"address":"0x6dfa6d2ba2f8d6e16e16e2e0d3cf4666cae62ea9","tx_count":145,"eth":{"value":"0.062127677454627135","dynamic":"-3.330727178046328926"},"nft":{"value":26,"dynamic":25,"collections":[false,false,false,false,false,false,false],"collections2":{"89seconds":false,"artBlocks":false,"boredApes":false,"cryptoPunks":false,"ksoids":false,"meebits":false,"omnimorphs":false}}},"floor":0.084},{"timestamp":1638966918,"price":0.084,"block_number":13764825,"account":{"address":"0xe9452a904e833d3e64b159581884d196e5ece123","tx_count":29,"eth":{"value":"0.049490166273437172","dynamic":"-0.379852882434481618"},"nft":{"value":27,"dynamic":20,"collections":[false,false,false,false,false,false,false],"collections2":{"89seconds":false,"artBlocks":false,"boredApes":false,"cryptoPunks":false,"ksoids":false,"meebits":false,"omnimorphs":false}}},"floor":0.084}]}