{"uuid":"58826d97-5905-4c47-874b-59564317ebab","token_id":4695,"color":3,"transactions":[{"timestamp":1634396451,"price":0.10301,"block_number":13429706,"account":{"address":"0xaa9aa561cb33c212ea3407385bc8b8da0318b7be","tx_count":282,"eth":{"value":"0.774931585584368411","dynamic":"0.727903999124875657"},"nft":{"value":71,"dynamic":71,"collections":[false,false,false,false,false,false,false],"collections2":{"89seconds":false,"artBlocks":false,"boredApes":false,"cryptoPunks":false,"ksoids":false,"meebits":false,"omnimorphs":false}}},"floor":0.10301},{"timestamp":1634994944,"price":0,"block_number":13473992,"account":{"address":"0x8b15df3466c42e8b4521da72aa1011291663ae91","tx_count":2,"eth":{"value":"0.091758486075912747","dynamic":"0.091758486075912747"},"nft":{"value":4,"dynamic":2,"collections":[false,false,false,false,false,false,false],"collections2":{"89seconds":false,"artBlocks":false,"boredApes":false,"cryptoPunks":false,"ksoids":false,"meebits":false,"omnimorphs":false}}},"floor":0.12150000000000001},{"timestamp":1635070790,"price":0.15,"block_number":13479603,"account":{"address":"0x04627e7835e4bbaa9f1af12802d7e9eb9124e8d1","tx_count":4,"eth":{"value":"0.49845569601528526","dynamic":"0.49845569601528526"},"nft":{"value":4,"dynamic":4,"collections":[false,false,false,false,false,false,false],"collections2":{"89seconds":false,"artBlocks":false,"boredApes":false,"cryptoPunks":false,"ksoids":false,"meebits":false,"omnimorphs":false}}},"floor":0.11178000000000002},{"timestamp":1637181947,"price":0.089,"block_number":13635220,"account":{"address":"0xb394f1aa30ba874df3ae6097bf4c2474b2d8f3ac","tx_count":5167,"eth":{"value":"13.720374597710856962","dynamic":"13.686882969359369921"},"nft":{"value":2761,"dynamic":1322,"collections":[false,false,false,false,false,false,false],"collections2":{"89seconds":false,"artBlocks":true,"boredApes":true,"cryptoPunks":true,"ksoids":false,"meebits":true,"omnimorphs":false}}},"floor":0.06804}]}