{"uuid":"01e909d0-c17f-4963-897d-f94099b1c451","token_id":4956,"color":5,"transactions":[{"timestamp":1634396556,"price":0.10301,"block_number":13429712,"account":{"address":"0x5e43bdfca1f1e5857d85b1a52302f99ef0b4d501","tx_count":11,"eth":{"value":"1.133307238097830662","dynamic":"1.133307238097830662"},"nft":{"value":5,"dynamic":5,"collections":[false,false,false,false,false,false,false],"collections2":{"89seconds":false,"artBlocks":false,"boredApes":false,"cryptoPunks":false,"ksoids":false,"meebits":false,"omnimorphs":false}}},"floor":0.10301},{"timestamp":1634400529,"price":0,"block_number":13430009,"account":{"address":"0x285841a324cb957d0b31b4d435390f7dffd949e5","tx_count":10,"eth":{"value":"1.055907413646656964","dynamic":"0.648592108475730563"},"nft":{"value":8,"dynamic":8,"collections":[false,false,false,false,false,false,false],"collections2":{"89seconds":false,"artBlocks":false,"boredApes":false,"cryptoPunks":false,"ksoids":false,"meebits":false,"omnimorphs":false}}},"floor":0.10301},{"timestamp":1634401884,"price":0.0001,"block_number":13430132,"account":{"address":"0x5e43bdfca1f1e5857d85b1a52302f99ef0b4d501","tx_count":14,"eth":{"value":"1.083472769405334856","dynamic":"1.083472769405334856"},"nft":{"value":5,"dynamic":5,"collections":[false,false,false,false,false,false,false],"collections2":{"89seconds":false,"artBlocks":false,"boredApes":false,"cryptoPunks":false,"ksoids":false,"meebits":false,"omnimorphs":false}}},"floor":0.10301},{"timestamp":1634405202,"price":0.14,"block_number":13430380,"account":{"address":"0x52db15ba307b9e4b58527da31802815920de14a6","tx_count":10,"eth":{"value":"1.93918724528900494","dynamic":"1.93918724528900494"},"nft":{"value":1,"dynamic":1,"collections":[false,false,false,false,false,false,false],"collections2":{"89seconds":false,"artBlocks":false,"boredApes":false,"cryptoPunks":false,"ksoids":false,"meebits":false,"omnimorphs":false}}},"floor":0.10350000000000001},{"timestamp":1634414078,"price":0.14,"block_number":13431024,"account":{"address":"0x5e43bdfca1f1e5857d85b1a52302f99ef0b4d501","tx_count":16,"eth":{"value":"1.73558548641386888","dynamic":"1.73558548641386888"},"nft":{"value":5,"dynamic":5,"collections":[false,false,false,false,false,false,false],"collections2":{"89seconds":false,"artBlocks":false,"boredApes":false,"cryptoPunks":false,"ksoids":false,"meebits":false,"omnimorphs":false}}},"floor":0.10301},{"timestamp":1635537935,"price":0.1,"block_number":13514100,"account":{"address":"0x4a1c6454d5d5b5ff0ddb6a2138a73fdebaa5afe4","tx_count":4,"eth":{"value":"0.0220362812","dynamic":"0.0220362812"},"nft":{"value":4,"dynamic":4,"collections":[false,false,false,false,false,false,false],"collections2":{"89seconds":false,"artBlocks":false,"boredApes":false,"cryptoPunks":false,"ksoids":false,"meebits":false,"omnimorphs":false}}},"floor":0.047709}]}