{"uuid":"f65a1855-4c8b-487a-8a3b-97a139a38f60","token_id":5678,"color":1,"transactions":[{"timestamp":1634397100,"price":0.10301,"block_number":13429757,"account":{"address":"0x0f60dacc38f963a9aee3151750b2b38931169c82","tx_count":120,"eth":{"value":"12.090817935957925266","dynamic":"-36.597156209352933308"},"nft":{"value":24,"dynamic":24,"collections":[false,false,false,false,false,false,false],"collections2":{"89seconds":false,"artBlocks":false,"boredApes":false,"cryptoPunks":false,"ksoids":false,"meebits":false,"omnimorphs":false}}},"floor":0.10301},{"timestamp":1634594456,"price":0.125,"block_number":13444323,"account":{"address":"0xce50d864327aee4ec2dde85a7fda202358a80189","tx_count":281,"eth":{"value":"3.268897626994670139","dynamic":"3.268897626994670139"},"nft":{"value":187,"dynamic":187,"collections":[false,false,false,false,false,false,false],"collections2":{"89seconds":false,"artBlocks":false,"boredApes":false,"cryptoPunks":false,"ksoids":false,"meebits":false,"omnimorphs":false}}},"floor":0.10807647929817085}]}