{"uuid":"71902a9a-2072-4a79-ae09-32a03b664a72","token_id":5898,"color":3,"transactions":[{"timestamp":1634397805,"price":0.10301,"block_number":13429796,"account":{"address":"0xe70987f1d4a8830d3c4cae40bc3f73ee5724fd18","tx_count":52,"eth":{"value":"0.442739307650444451","dynamic":"0.442739307650444451"},"nft":{"value":119,"dynamic":119,"collections":[false,false,false,false,false,false,false],"collections2":{"89seconds":false,"artBlocks":false,"boredApes":false,"cryptoPunks":false,"ksoids":false,"meebits":false,"omnimorphs":false}}},"floor":0.10301},{"timestamp":1640702459,"price":0.055,"block_number":13894332,"account":{"address":"0x02f26a1ff2d800406cbf4e3d959ef3c047c7ed15","tx_count":39,"eth":{"value":"0.011544935298368544","dynamic":"0.010130066047076171"},"nft":{"value":14,"dynamic":5,"collections":[false,false,false,false,false,false,false],"collections2":{"89seconds":false,"artBlocks":false,"boredApes":false,"cryptoPunks":false,"ksoids":false,"meebits":false,"omnimorphs":false}}},"floor":0.055}]}