{"uuid":"6400bc7a-77a8-4cc3-a78f-750dabad1f16","token_id":6288,"color":3,"transactions":[{"timestamp":1634399080,"price":0.10301,"block_number":13429889,"account":{"address":"0x68c99afa80a2f538ede0626117e99acd8fea17bd","tx_count":6,"eth":{"value":"0.335287115597682628","dynamic":"0.335287115597682628"},"nft":{"value":5,"dynamic":5,"collections":[false,false,false,false,false,false,false],"collections2":{"89seconds":false,"artBlocks":false,"boredApes":false,"cryptoPunks":false,"ksoids":false,"meebits":false,"omnimorphs":false}}},"floor":0.10301},{"timestamp":1634450133,"price":0.165,"block_number":13433704,"account":{"address":"0x53df2d70e4982d9b45a3fcb5cad07b9249211aaa","tx_count":100,"eth":{"value":"0.171362408756902732","dynamic":"-0.208022907309487382"},"nft":{"value":2,"dynamic":2,"collections":[false,false,false,false,false,false,false],"collections2":{"89seconds":false,"artBlocks":false,"boredApes":false,"cryptoPunks":false,"ksoids":false,"meebits":false,"omnimorphs":false}}},"floor":0.185},{"timestamp":1636274417,"price":0.22,"block_number":13568358,"account":{"address":"0x903435bb40a3955aba055488321d0016525f1c2b","tx_count":177,"eth":{"value":"9.350591906552438758","dynamic":"8.969568516635081374"},"nft":{"value":1,"dynamic":1,"collections":[false,false,false,false,false,false,false],"collections2":{"89seconds":false,"artBlocks":false,"boredApes":false,"cryptoPunks":false,"ksoids":false,"meebits":false,"omnimorphs":false}}},"floor":0.07301},{"timestamp":1638800114,"price":0.23,"block_number":13752771,"account":{"address":"0x999a6042c1121800d9a152f631e76796e8f6d7e2","tx_count":46,"eth":{"value":"0.121081372178001307","dynamic":"0.119404455388780586"},"nft":{"value":0,"dynamic":0,"collections":[false,false,false,false,false,false,false],"collections2":{"89seconds":false,"artBlocks":false,"boredApes":false,"cryptoPunks":false,"ksoids":false,"meebits":false,"omnimorphs":false}}},"floor":0.09},{"timestamp":1638884854,"price":0.23,"block_number":13758872,"account":{"address":"0xde0712a6783264f6911015bc5a85029b97ed15e5","tx_count":3,"eth":{"value":"0.251851599111586747","dynamic":"0.251851599111586747"},"nft":{"value":0,"dynamic":0,"collections":[false,false,false,false,false,false,false],"collections2":{"89seconds":false,"artBlocks":false,"boredApes":false,"cryptoPunks":false,"ksoids":false,"meebits":false,"omnimorphs":false}}},"floor":0.08},{"timestamp":1638885654,"price":0.23,"block_number":13758926,"account":{"address":"0x8f8d9f3a7502691e2fd877cb82cea143d9373452","tx_count":3,"eth":{"value":"0.054558974251698825","dynamic":"0.054558974251698825"},"nft":{"value":0,"dynamic":0,"collections":[false,false,false,false,false,false,false],"collections2":{"89seconds":false,"artBlocks":false,"boredApes":false,"cryptoPunks":false,"ksoids":false,"meebits":false,"omnimorphs":false}}},"floor":0.08},{"timestamp":1638886111,"price":0.27,"block_number":13758962,"account":{"address":"0x53df2d70e4982d9b45a3fcb5cad07b9249211aaa","tx_count":127,"eth":{"value":"0.406377482086857082","dynamic":"0.149329326624123338"},"nft":{"value":2,"dynamic":2,"collections":[false,false,false,false,false,false,false],"collections2":{"89seconds":false,"artBlocks":false,"boredApes":false,"cryptoPunks":false,"ksoids":false,"meebits":false,"omnimorphs":false}}},"floor":0.08}]}