{"uuid":"4ee648a9-c9cf-48c8-9c5d-a895ccf74aea","token_id":6792,"color":3,"transactions":[{"timestamp":1634401676,"price":0.10301,"block_number":13430114,"account":{"address":"0x25392025806c7527e619f94264e96cffff8fd93e","tx_count":3,"eth":{"value":"2.770493188034327232","dynamic":"2.770493188034327232"},"nft":{"value":3,"dynamic":3,"collections":[false,false,false,false,false,false,false],"collections2":{"89seconds":false,"artBlocks":false,"boredApes":false,"cryptoPunks":false,"ksoids":false,"meebits":false,"omnimorphs":false}}},"floor":0.10301}]}