{"uuid":"3b27073f-10ad-411d-ad05-006355972bb1","token_id":9270,"color":3,"transactions":[{"timestamp":1634408705,"price":0.10301,"block_number":13430633,"account":{"address":"0x00c0798c0df1e87069417e76b8ca4fa089d051f1","tx_count":1762,"eth":{"value":"229.30204647191378449","dynamic":"-10.98211956372723877"},"nft":{"value":0,"dynamic":0,"collections":[false,false,false,false,false,false,false],"collections2":{"89seconds":false,"artBlocks":false,"boredApes":false,"cryptoPunks":false,"ksoids":false,"meebits":false,"omnimorphs":false}}},"floor":0.10301},{"timestamp":1635245344,"price":0.18,"block_number":13492554,"account":{"address":"0x99a0c2ddb3b161be4a442c98ea81a76d0e4948e6","tx_count":6,"eth":{"value":"0.323413250463341034","dynamic":"0.323413250463341034"},"nft":{"value":2,"dynamic":2,"collections":[false,false,false,false,false,false,false],"collections2":{"89seconds":false,"artBlocks":false,"boredApes":false,"cryptoPunks":false,"ksoids":false,"meebits":false,"omnimorphs":false}}},"floor":0.11259000000000002}]}