{"uuid":"db7576b0-f1cd-4ad7-ae75-3828a4703b2d","token_id":9287,"color":3,"transactions":[{"timestamp":1634408705,"price":0.10301,"block_number":13430633,"account":{"address":"0x88f516c04969f470888473458b5e09342da08b7a","tx_count":2080,"eth":{"value":"1.443968674155505344","dynamic":"-0.91729168238308222"},"nft":{"value":0,"dynamic":0,"collections":[false,false,false,false,false,false,false],"collections2":{"89seconds":false,"artBlocks":true,"boredApes":false,"cryptoPunks":false,"ksoids":false,"meebits":false,"omnimorphs":false}}},"floor":0.10301},{"timestamp":1634665936,"price":0.15,"block_number":13449613,"account":{"address":"0x167ea81e4d262a9c42ba5acb1ac7994ad6520048","tx_count":91,"eth":{"value":"0.063960543512933657","dynamic":"-1.391348653832298914"},"nft":{"value":1,"dynamic":1,"collections":[false,false,false,false,false,false,false],"collections2":{"89seconds":false,"artBlocks":false,"boredApes":false,"cryptoPunks":false,"ksoids":false,"meebits":false,"omnimorphs":false}}},"floor":0.10301}]}