{"uuid":"22cd7b7b-e766-4cea-a112-2f830417845a","token_id":9581,"color":4,"transactions":[{"timestamp":1634409002,"price":0.10301,"block_number":13430651,"account":{"address":"0x926cbb618bc16e8cd27546a583f77da12294ac78","tx_count":185,"eth":{"value":"0.911930034060136216","dynamic":"0.634345992610154216"},"nft":{"value":0,"dynamic":0,"collections":[false,false,false,false,false,false,false],"collections2":{"89seconds":false,"artBlocks":false,"boredApes":false,"cryptoPunks":false,"ksoids":false,"meebits":false,"omnimorphs":false}}},"floor":0.10301},{"timestamp":1640930049,"price":0.039,"block_number":13911355,"account":{"address":"0x938f7c47a2dafd25959ed334649fd1b8172cd854","tx_count":31,"eth":{"value":"3.407929354342977717","dynamic":"3.401523015295914421"},"nft":{"value":9,"dynamic":9,"collections":[false,false,false,false,false,false,false],"collections2":{"89seconds":false,"artBlocks":true,"boredApes":false,"cryptoPunks":false,"ksoids":false,"meebits":false,"omnimorphs":false}}},"floor":0.036},{"timestamp":1640944402,"price":0.045,"block_number":13912450,"account":{"address":"0x258b3bab0aaec3d95ab9c5382281ea09dedea61b","tx_count":188,"eth":{"value":"3.110406940322528701","dynamic":"2.888053479610836127"},"nft":{"value":97,"dynamic":26,"collections":[false,false,false,false,false,false,false],"collections2":{"89seconds":false,"artBlocks":false,"boredApes":true,"cryptoPunks":false,"ksoids":false,"meebits":false,"omnimorphs":false}}},"floor":0.045}]}