{"uuid":"ea683745-8877-4a36-b93f-c004a8b59a36","token_id":10031,"color":1,"transactions":[{"timestamp":1634409393,"price":0.10301,"block_number":13430673,"account":{"address":"0xd2a102b745a1f3771cd0ce1ee67c3c0aa594157b","tx_count":186,"eth":{"value":"0.184312482071157286","dynamic":"-0.048889969889796232"},"nft":{"value":0,"dynamic":0,"collections":[false,false,false,false,false,false,false],"collections2":{"89seconds":false,"artBlocks":false,"boredApes":false,"cryptoPunks":false,"ksoids":false,"meebits":false,"omnimorphs":false}}},"floor":0.10301},{"timestamp":1634411363,"price":0.178,"block_number":13430816,"account":{"address":"0x09be9ab0eb61327d26904bae69efdc6633d5eec8","tx_count":3748,"eth":{"value":"26.702515389740019265","dynamic":"18.615012371249075904"},"nft":{"value":633,"dynamic":591,"collections":[false,false,false,false,false,false,false],"collections2":{"89seconds":false,"artBlocks":false,"boredApes":true,"cryptoPunks":false,"ksoids":false,"meebits":true,"omnimorphs":false}}},"floor":0.10301}]}